zbus_cli/__init__.py
zbus_cli/cli.py
zbus_cli/command/__init__.py
zbus_cli/helper/__init__.py
zbus_cli/helper/entry_points.py
zbus_cli/helper/plugin_system.py
zbus_cli/verb/__init__.py
zbus_service/__init__.py
zbus_service/command/__init__.py
zbus_service/command/service.py
zbus_service/verb/__init__.py
zbus_service/verb/call.py
zbus_topic/__init__.py
zbus_topic/command/__init__.py
zbus_topic/command/topic.py
zbus_topic/verb/__init__.py
zbus_topic/verb/delay.py
zbus_topic/verb/echo.py
zbus_topic/verb/hz.py
zbus_topic/verb/pub.py
zbus_cli-0.0.7.dist-info/METADATA
zbus_cli-0.0.7.dist-info/WHEEL
zbus_cli-0.0.7.dist-info/entry_points.txt
zbus_cli-0.0.7.dist-info/top_level.txt
zbus_cli-0.0.7.dist-info/RECORD
