Metadata-Version: 2.1
Name: zbus-cli
Version: 0.0.7
Summary: Framework for ZBUS command line tools.
Author: huangxin
Author-email: huangxin13066@cvte.com
Classifier: Programming Language :: Python :: 3
Classifier: License :: OSI Approved :: MIT License
Classifier: Operating System :: OS Independent
Requires-Python: >=3.7, <4
Requires-Dist: msgpack
Requires-Dist: pyzmq
Provides-Extra: completion
Requires-Dist: argcomplete3 ; extra == 'completion'
